{
  "name": "ropademoda.mx",
  "intents": [
    {
      "intent": "General_Greetings",
      "examples": [
        {
          "text": "Buenos días, podemos empezar la conversación?"
        },
        {
          "text": "¿Cómo está? / Oye, ¿Qué tal?"
        },
        {
          "text": "¡Estoy feliz de poder hablar contigo por primera vez!"
        },
        {
          "text": "¿Estás ahí?"
        },
        {
          "text": "Hey, ¿cómo te va?"
        },
        {
          "text": "Hola, amigo mío."
        },
        {
          "text": "Hola, Cómo estás el día de hoy?"
        },
        {
          "text": "Hola, ¿Cómo estás?"
        },
        {
          "text": "Hola, ¿Cómo te sientes?"
        },
        {
          "text": "Hola, Cómo va todo?"
        },
        {
          "text": "Hola, me conectas con el soporte tecnico?"
        },
        {
          "text": "Hola, podrías responder mi pregunta?"
        },
        {
          "text": "Hola ¿puedes ayudarme?"
        },
        {
          "text": "Hola, quien me puede atender?"
        },
        {
          "text": "Hola, Señor."
        },
        {
          "text": "Quién eres?"
        },
        {
          "text": "Sigues aquí?"
        },
        {
          "text": "Tienes un momento, por favor?"
        },
        {
          "text": "Buenas noches."
        }
      ],
      "description": "Saluda al bot."
    },
    {
      "intent": "ubicacion_tiendas",
      "examples": [
        {
          "text": "donde está la tienda mas cercana?"
        },
        {
          "text": "donde están ubicadas sus tiendas?"
        },
        {
          "text": "quiero comprar en la tienda física"
        },
        {
          "text": "donde puedo comprar sus productos?"
        },
        {
          "text": "tienen tiendas físicas?"
        },
        {
          "text": "como puedo llegar a la tienda?"
        },
        {
          "text": "en que zonas de la ciudad tienen tiendas?"
        },
        {
          "text": "me puedes decir la dirección donde se encuentran?"
        }
      ],
      "description": "Entender donde puede encontrar una tienda"
    },
    {
      "intent": "precio_producto",
      "examples": [
        {
          "text": "tienes promociones para"
        },
        {
          "text": "cuanto cuesta una playera?"
        },
        {
          "text": "puedes darme precios?"
        },
        {
          "text": "que tan caros son los productos"
        },
        {
          "text": "quiero cotizar"
        },
        {
          "text": "cuanto cuesta"
        },
        {
          "text": "sabes el precio?"
        },
        {
          "text": "hay algun descuento"
        }
      ]
    },
    {
      "intent": "General_Agent_Capabilities",
      "examples": [
        {
          "text": "Tengo algunas preguntas y necesito ayuda, ¿puedo recibir ayuda?"
        },
        {
          "text": "¿Con qué categorías de problemas están capaz de ayudarme?"
        },
        {
          "text": "¿Con qué categorías de problemas me puedes ayudar?"
        },
        {
          "text": "¿Cuáles son las opciones disponibles si estoy usando agente virtual?"
        },
        {
          "text": "Tengo varios problemas y necesito saber con qué me puede ayudar."
        },
        {
          "text": "Tengo algunos problemas y quiero algo de información sobre cómo conseguir ayuda."
        },
        {
          "text": "¿Qué tipo de preguntas puedes contestar? ¿Y cuáles son tus limitaciones de respuestas?"
        },
        {
          "text": "¿Qué tipo de información y problemas puedes resolver para mí?"
        },
        {
          "text": "¿Qué tipo de cosas puede hacer por mí?"
        },
        {
          "text": "¿Cómo funciona el filtro en la pantalla de capacidades?"
        },
        {
          "text": "¿Puedo tener una lista de temas disponibles, con los que puedes ayudarme?"
        },
        {
          "text": "¿Puedes esperar un poquito?"
        },
        {
          "text": "¿Puedes darme una lista de temas de cosas con las que puedes ayudarme?"
        },
        {
          "text": "¿Puedes ayudarme en cómo iniciar sesión en Virtual Agent?"
        },
        {
          "text": "¿Podría esperar un segundo por favor?"
        },
        {
          "text": "¿Podría darme una lista de temas con las que puede ayudarme?"
        },
        {
          "text": "¿Podría esperar un momento por favor?"
        },
        {
          "text": "¿Qué pasa si quiero cambiar la respuesta de texto para una intención?"
        },
        {
          "text": "¿Qué hace un agente digital? ¿Para qué te uso?"
        },
        {
          "text": "¿Qué clase de cosas haces?"
        },
        {
          "text": "qué sabes hacer?"
        }
      ],
      "description": "Solicitar capacidades del bot."
    },
    {
      "intent": "General_Human_or_Bot",
      "examples": [
        {
          "text": "Eres un operador virtual o vivo?"
        },
        {
          "text": "Tu eres un agente virtual o real?"
        },
        {
          "text": "Cómo puedo contactar con un ser vivo?"
        },
        {
          "text": "Sería posible hablar con una persona?"
        },
        {
          "text": "quién eres?"
        },
        {
          "text": "Eres una máquina o una persona real?"
        },
        {
          "text": "Eres un agente virtual?"
        },
        {
          "text": "Dejame hablar con un agente."
        },
        {
          "text": "Creo que es mejor hablar con una persona."
        },
        {
          "text": "No quiero hablar con el agente virtual."
        },
        {
          "text": "Con quién estoy hablando?"
        },
        {
          "text": "Podría hablar con un agente virutal?"
        },
        {
          "text": "Preferiría hablar con un agente virutal."
        },
        {
          "text": "Puedes decirme, si eres vivo o virutal?"
        },
        {
          "text": "Puedes transferirme a un agente real?"
        },
        {
          "text": "Puedo hablar con una persona real?"
        },
        {
          "text": "Me confirmas si hablo con un agente virtual o con un agente real?"
        },
        {
          "text": "Quiero hablar con una persona."
        },
        {
          "text": "Necesito hablar con alquien vivo."
        },
        {
          "text": "Hablo con una persona?"
        },
        {
          "text": "Hablo con una máquina?"
        }
      ],
      "description": "Preguntar si habla con un humano o un bot."
    }
  ],
  "entities": [
    {
      "entity": "TipoPrenda",
      "values": [
        {
          "type": "synonyms",
          "value": "Bottom",
          "synonyms": [
            "pantalón",
            "bermuda",
            "falda",
            "vestido"
          ]
        },
        {
          "type": "synonyms",
          "value": "Exteriores",
          "synonyms": [
            "chamarra",
            "bufanda",
            "guantes"
          ]
        },
        {
          "type": "synonyms",
          "value": "Joyería",
          "synonyms": [
            "reloj",
            "collar",
            "pulsera",
            "anillo",
            "aretes"
          ]
        },
        {
          "type": "synonyms",
          "value": "Top",
          "synonyms": [
            "playera",
            "camisa",
            "blusa"
          ]
        },
        {
          "type": "synonyms",
          "value": "Deportiva",
          "synonyms": [
            "short",
            "pants"
          ]
        }
      ],
      "fuzzy_match": true
    },
    {
      "entity": "sys-date",
      "values": []
    }
  ],
  "language": "es",
  "metadata": {
    "api_version": {
      "major_version": "v1",
      "minor_version": "2018-09-20"
    }
  },
  "description": "Asistente virtual para apoyar en la compra de ropa, tanto a través del portal de e-commerce, como en la tienda física.",
  "dialog_nodes": [
    {
      "type": "response_condition",
      "output": {
        "text": {
          "values": [
            "Buenas noches",
            "Buena noche",
            "Excelente noche"
          ],
          "selection_policy": "random"
        }
      },
      "parent": "node_4_1545229566258",
      "metadata": {},
      "conditions": "$CURRENT_TIME.after('18:00:00')",
      "dialog_node": "node_8_1545229630111",
      "previous_sibling": "node_7_1545229619725"
    },
    {
      "type": "response_condition",
      "output": {
        "text": {
          "values": [
            "Buenas tardes",
            "Buena tarde",
            "Excelente tarde"
          ],
          "selection_policy": "random"
        }
      },
      "parent": "node_4_1545229566258",
      "metadata": {},
      "conditions": "$CURRENT_TIME.after('12:00:00')",
      "dialog_node": "node_7_1545229619725",
      "previous_sibling": "node_5_1545229574221"
    },
    {
      "type": "response_condition",
      "output": {
        "text": {
          "values": [
            "Buenos días",
            "Buen día",
            "Excelente día"
          ],
          "selection_policy": "random"
        }
      },
      "parent": "node_4_1545229566258",
      "metadata": {},
      "conditions": "$CURRENT_TIME.before('12:00:00')",
      "dialog_node": "node_5_1545229574221"
    },
    {
      "type": "response_condition",
      "output": {},
      "parent": "Bienvenido",
      "disabled": true,
      "metadata": {},
      "dialog_node": "node_6_1545229584838",
      "previous_sibling": "node_4_1545229566258"
    },
    {
      "type": "standard",
      "output": {},
      "parent": "Bienvenido",
      "metadata": {
        "_customization": {
          "mcr": true
        }
      },
      "conditions": "true",
      "dialog_node": "node_4_1545229566258",
      "digress_out": "allow_all"
    },
    {
      "type": "standard",
      "title": "Identifica Categoría",
      "output": {},
      "parent": "node_6_1521642082098",
      "metadata": {
        "_customization": {
          "mcr": true
        }
      },
      "conditions": "@TipoPrenda",
      "dialog_node": "node_7_1521642116642",
      "digress_out": "allow_all"
    },
    {
      "type": "response_condition",
      "output": {
        "text": {
          "values": [
            "Voy a buscar las mejores promociones"
          ],
          "selection_policy": "sequential"
        }
      },
      "parent": "node_7_1521642116642",
      "context": {
        "BANDERA_COTIZAR": "true",
        "CATEGORIA_PRODUCTO": "@TipoPrenda"
      },
      "metadata": {},
      "conditions": "$CANAL==\"WEB\"",
      "dialog_node": "node_13_1521642586805",
      "previous_sibling": "node_12_1521642403104"
    },
    {
      "type": "response_condition",
      "output": {
        "text": {
          "values": [
            "Siempre tenemos promociones, checa nuestro website ropamoda.mx para conocerlas"
          ],
          "selection_policy": "sequential"
        }
      },
      "parent": "node_7_1521642116642",
      "context": {
        "bandera_cotizar": "true",
        "categoria_producto": "top"
      },
      "metadata": {},
      "conditions": "anything_else",
      "dialog_node": "node_9_1521642222157",
      "previous_sibling": "node_13_1521642586805"
    },
    {
      "type": "standard",
      "title": "Mostrar Promociones",
      "output": {
        "text": {
          "values": [
            "Para la prenda $PRENDA encontré la siguiente promoción: $PROMOCIONES"
          ],
          "selection_policy": "sequential"
        }
      },
      "parent": "node_7_1521642116642",
      "metadata": {},
      "conditions": "$PROMOCIONES_OK!=null",
      "dialog_node": "node_12_1521642403104"
    },
    {
      "type": "response_condition",
      "output": {
        "text": {
          "values": [
            "Tenemos tiendas por toda la ciudad, algunas de ellas son Perisur, Santa Fe y Centro Coyoacán"
          ],
          "selection_policy": "sequential"
        }
      },
      "parent": "node_3_1521641674258",
      "metadata": {},
      "conditions": "anything_else",
      "dialog_node": "node_4_1545232316113",
      "previous_sibling": "node_3_1545232292747"
    },
    {
      "type": "response_condition",
      "output": {
        "text": {
          "values": [
            "Aquí tienes un mapa con la ubicación."
          ],
          "selection_policy": "sequential"
        }
      },
      "parent": "node_3_1521641674258",
      "context": {
        "BANDERA_UBICACION": "true"
      },
      "metadata": {},
      "conditions": "$CANAL==\"WEB\"",
      "dialog_node": "node_3_1545232292747"
    },
    {
      "type": "standard",
      "output": {
        "text": {
          "values": [],
          "selection_policy": "sequential"
        }
      },
      "metadata": {},
      "next_step": {
        "behavior": "jump_to",
        "selector": "body",
        "dialog_node": "node_7_1521642116642"
      },
      "conditions": "#precio_producto && @TipoPrenda",
      "digress_in": "does_not_return",
      "dialog_node": "node_1_1545231826569",
      "previous_sibling": "node_14_1521642643437"
    },
    {
      "type": "standard",
      "title": "Es Humano?",
      "output": {
        "text": {
          "values": [
            "Soy un assistente virtual intentando darte el mejor servicio, lo más rápido posible. Estoy disponible las 24 horas del día para ti"
          ],
          "selection_policy": "sequential"
        }
      },
      "metadata": {},
      "conditions": "#General_Human_or_Bot",
      "dialog_node": "node_2_1521641616727",
      "previous_sibling": "Bienvenido"
    },
    {
      "type": "standard",
      "output": {
        "text": {
          "values": [],
          "selection_policy": "sequential"
        }
      },
      "metadata": {},
      "next_step": {
        "behavior": "jump_to",
        "selector": "body",
        "dialog_node": "node_7_1521642116642"
      },
      "conditions": "@TipoPrenda",
      "dialog_node": "node_2_1545232069302",
      "previous_sibling": "node_6_1521642082098"
    },
    {
      "type": "standard",
      "title": "En otras cosas",
      "output": {
        "text": {
          "values": [
            "No le he entendido. Intente reformular la consulta.",
            "¿Puede expresarse con otras palabras? No le he entendido.",
            "No entendí el significado."
          ],
          "selection_policy": "sequential"
        }
      },
      "metadata": {},
      "conditions": "anything_else",
      "dialog_node": "En otras cosas",
      "previous_sibling": "node_1_1521640209725"
    },
    {
      "type": "standard",
      "title": "Ubicar tiendas",
      "output": {},
      "metadata": {
        "_customization": {
          "mcr": true
        }
      },
      "conditions": "#ubicacion_tiendas",
      "digress_in": "does_not_return",
      "dialog_node": "node_3_1521641674258",
      "digress_out": "allow_all",
      "previous_sibling": "node_2_1545232069302"
    },
    {
      "type": "standard",
      "title": "Cotizar",
      "output": {
        "text": {
          "values": [
            "Qué tipo de prenda te interesa?"
          ],
          "selection_policy": "sequential"
        }
      },
      "metadata": {},
      "conditions": "#precio_producto",
      "dialog_node": "node_6_1521642082098",
      "previous_sibling": "node_1_1545231826569"
    },
    {
      "type": "standard",
      "title": "Capacidades",
      "output": {
        "text": {
          "values": [
            "Ahora mismo puedo ayudarte a cotizar un tipo de prenda: playeras, faldas, pantalones, pero estoy siendo entrenado para mucho más."
          ],
          "selection_policy": "sequential"
        }
      },
      "metadata": {},
      "conditions": "#General_Agent_Capabilities",
      "dialog_node": "node_14_1521642643437",
      "previous_sibling": "node_2_1521641616727"
    },
    {
      "type": "standard",
      "title": "Saludo",
      "output": {
        "text": {
          "values": [
            "¡Hola!",
            "Parece que ya me saludaste antes",
            "Saludar es lo único que sabes hacer?"
          ],
          "selection_policy": "sequential"
        }
      },
      "metadata": {},
      "conditions": "#General_Greetings",
      "digress_in": "does_not_return",
      "dialog_node": "node_1_1521640209725",
      "previous_sibling": "node_3_1521641674258"
    },
    {
      "type": "standard",
      "title": "Bienvenido",
      "output": {
        "text": {
          "values": [
            "Hola $USERNAME",
            "Bienvenid@ $USERNAME",
            "Qué tal $USERNAME"
          ],
          "selection_policy": "random"
        }
      },
      "context": {
        "CURRENT_TIME": "<? now().split(' ')[1] ?>"
      },
      "metadata": {
        "_customization": {
          "mcr": false
        }
      },
      "next_step": {
        "behavior": "skip_user_input"
      },
      "conditions": "welcome",
      "digress_in": "does_not_return",
      "dialog_node": "Bienvenido",
      "digress_out": "allow_all"
    }
  ],
  "workspace_id": "128d1aee-a0de-45f1-bd58-f38c39254d6f",
  "counterexamples": [],
  "learning_opt_out": false,
  "status": "Available"
}